{
  "id": "cabin_nightstand_cherry",
  "item": {
    "description": "A rustic cherry nightstand.",
    "name": "Rustic Cabin Nightstand",
    "icon_sprite": "spr_ui_item_furniture_cabin_nightstand_v1",
    "tags": [
      "furniture",
      "nightstand",
      "rustic_cabin_set"
    ],
    "value": {
      "bin": "self.recipe * 1.1",
      "store": 200
    },
    "recipe": {
      "level_requirement": 4,
      "ingredients": [
        {
          "count": 30,
          "item": "basic_wood"
        },
        {
          "count": 5,
          "item": "ore_stone"
        },
        {
          "count": 5,
          "item": "sap"
        }
      ],
      "duration": {
        "hours": 0,
        "minutes": 30
      }
    }
  }
}