{
  "id": "crop_faux_tulip",
  "item": {
    "description": "A decorative faux tulip.",
    "name": "Faux Tulip",
    "icon_sprite": "spr_ui_item_decor_crop_faux_tulip",
    "tags": [
      "furniture",
      "farm_decor",
      "faux_spring_plants_set"
    ],
    "value": {
      "bin": "self.recipe*1.1"
    },
    "recipe": {
      "level_requirement": 16,
      "ingredients": [
        {
          "count": 4,
          "item": "tulip"
        }
      ],
      "duration": {
        "hours": 0,
        "minutes": 40
      }
    }
  }
}