{
  "id": "mayonnaise",
  "item": {
    "description": "A popular condiment made from chicken eggs. Used in a variety of cooking recipes.",
    "name": "Mayonnaise",
    "icon_sprite": "spr_ui_item_mayonnaise",
    "tags": [
      "milling",
      "animal_product",
      "ranching"
    ],
    "value": {
      "bin": 90
    },
    "recipe": {
      "ingredients": [
        {
          "item": "egg",
          "count": 2
        }
      ],
      "duration": {
        "hours": 0,
        "minutes": 20
      }
    }
  }
}