{
  "id": "miners_ruby_rock",
  "item": {
    "description": "A decorative ruby rock.",
    "name": "Ornamental Ruby Rock",
    "icon_sprite": "spr_ui_item_furniture_ruby_rock",
    "tags": [
      "furniture",
      "mineshaft_set",
      "misc_furniture"
    ],
    "value": {
      "bin": "self.recipe * 1.1"
    },
    "recipe": {
      "level_requirement": 2,
      "ingredients": [
        {
          "count": 10,
          "item": "ore_stone"
        },
        {
          "count": 3,
          "item": "ore_ruby"
        },
        {
          "count": 3,
          "item": "red_toadstool"
        }
      ],
      "duration": {
        "hours": 0,
        "minutes": 30
      }
    }
  }
}