{
  "id": "monster_cookie",
  "item": {
    "description": "items/other/cooked_dishes/monster_cookie/description",
    "name": "items/other/cooked_dishes/monster_cookie/name",
    "icon_sprite": "spr_ui_item_monster_cookie",
    "tags": [
      "food",
      "baked_dessert"
    ],
    "value": {
      "store": 250
    },
    "recipe": {
      "level_requirement": 10,
      "ingredients": [
        {
          "count": 1,
          "item": "monster_powder"
        },
        {
          "count": 1,
          "item": "monster_core"
        },
        {
          "count": 1,
          "item": "sugar"
        }
      ],
      "duration": {
        "hours": 0,
        "minutes": 40
      }
    }
  }
}