{
  "id": "mushroom_rice",
  "item": {
    "description": "This fluffy mushroom rice has a nutty, toasted flavor.",
    "name": "Mushroom Rice",
    "icon_sprite": "spr_ui_item_mushroomrice",
    "tags": [
      "food",
      "simmered_dish",
      "mushroomy",
      "no_inn_plate"
    ],
    "value": {
      "store": 280
    },
    "recipe": {
      "level_requirement": 14,
      "ingredients": [
        {
          "count": 1,
          "item": "morel_mushroom"
        },
        {
          "count": 1,
          "item": "rice"
        },
        {
          "count": 1,
          "item": "soy_sauce"
        }
      ],
      "duration": {
        "hours": 0,
        "minutes": 30
      }
    }
  }
}