{
  "id": "ornate_rug_small_cream",
  "item": {
    "description": "A small cream colored ornate rug with a rectangular shape.",
    "name": "Ornate Small Rug",
    "icon_sprite": "spr_ui_item_decor_ornate_rug_small_cream",
    "tags": [
      "furniture",
      "small_rug",
      "ornate_rug_set"
    ],
    "value": {
      "bin": "self.recipe * 1.1"
    },
    "recipe": {
      "level_requirement": 4,
      "ingredients": [
        {
          "count": 1,
          "item": "rabbit_wool"
        },
        {
          "count": 1,
          "item": "duck_feather"
        }
      ],
      "duration": {
        "hours": 0,
        "minutes": 20
      }
    }
  }
}